{
  "version": "0.2",
  "language": "en",
  "words": [
    "LIFE",
    "Mondragon",
    "Ithaca",
    "bioregional",
    "bioregionalism",
    "regenerative",
    "stewardship",
    "cooperatives",
    "blockchain",
    "cryptocurrency",
    "tokenomics",
    "gamification",
    "crowdsourcing",
    "crowdfunding",
    "opensource",
    "fullstack",
    "frontend",
    "backend",
    "API",
    "APIs",
    "JSON",
    "YAML",
    "Markdown",
    "GitHub",
    "GitLab",
    "DevOps",
    "CI/CD",
    "OAuth",
    "JWT",
    "HTTPS",
    "TLS",
    "AES",
    "SHA",
    "RSA",
    "GDPR",
    "CCPA",
    "AML",
    "KYC",
    "DAO",
    "DeFi",
    "NFT",
    "Ethereum",
    "Solidity",
    "Hyperledger",
    "Fabric",
    "Polygon",
    "Arbitrum",
    "troymork",
    "LifeExponential",
    "Manus",
    "Buckminster",
    "Fuller",
    "Elinor",
    "Ostrom",
    "sociocratic",
    "sociocracy",
    "holacracy",
    "permaculture",
    "biomimicry",
    "cradle",
    "lifecycle",
    "upcycling",
    "downcycling",
    "circularity",
    "symbiosis",
    "symbiotic",
    "mutualism",
    "commensalism",
    "mycorrhizal",
    "mycelium",
    "rhizome",
    "rhizomatic",
    "autopoiesis",
    "autopoietic",
    "cybernetics",
    "systemics",
    "metamodernism",
    "metamodern",
    "posthuman",
    "posthumanism",
    "transhumanism",
    "techno",
    "optimism",
    "pessimism",
    "solutionism",
    "accelerationism",
    "degrowth",
    "postgrowth",
    "wellbeing",
    "eudaimonia",
    "ubuntu",
    "buen",
    "vivir",
    "sumak",
    "kawsay",
    "pachamama",
    "gaia",
    "noosphere",
    "technosphere",
    "anthropocene",
    "capitalocene",
    "chthulucene",
    "plantationocene",
    "symbiocene"
  ],
  "ignorePaths": [
    "node_modules/**",
    ".git/**",
    "*.png",
    "*.jpg",
    "*.jpeg",
    "*.gif",
    "*.svg",
    "*.pdf",
    "*.zip",
    "package-lock.json",
    "yarn.lock"
  ],
  "ignoreRegExpList": [
    "/\\b[A-Z]{2,}\\b/g",
    "/\\b\\d+\\b/g",
    "/https?:\\/\\/[^\\s]+/g",
    "/[a-zA-Z0-9._%+-]+@[a-zA-Z0-9.-]+\\.[a-zA-Z]{2,}/g"
  ]
}

